specfit/__init__.py
specfit/inference.py
specfit/natural_spline.py
specfit/posterior_helper.py
specfit/splines.py
specfit-0.5.0b2.dist-info/METADATA
specfit-0.5.0b2.dist-info/WHEEL
specfit-0.5.0b2.dist-info/licenses/LICENSE
specfit-0.5.0b2.dist-info/RECORD
