Metadata-Version: 2.3
Name: specfit
Version: 0.5.0b2
Summary: Infer polynomial spectral models with covariancess
Project-URL: Homepage, https://github.com/tmolteno/specfit
Project-URL: Issues, https://github.com/tmolteno/specfit/issues
Author-email: Tim Molteno <tim@elec.ac.nz>
License-File: LICENSE
Classifier: License :: OSI Approved :: MIT License
Classifier: Operating System :: OS Independent
Classifier: Programming Language :: Python :: 3
Requires-Python: >=3.8
Requires-Dist: arviz
Requires-Dist: astropy
Requires-Dist: h5py
Requires-Dist: matplotlib
Requires-Dist: pymc
Requires-Dist: sympy
